project/src/display.vhdl
library ieee;
use ieee.std_logic_1164.all;
use ieee.numeric_std.all;

entity display is
  port  (
        clk     :   in    std_logic;
        rst     :   in    std_logic;
        en      :   in    std_logic;
        input1  :   in    std_logic_vector(4 downto 0);
        input2  :   in    std_logic_vector(4 downto 0);
        input3  :   in    std_logic_vector(4 downto 0);
        seg     :   out   std_logic_vector(2 downto 0);
        led     :   out   std_logic_vector(7 downto 0)
        );
end entity;

architecture rtl of display is

  signal  contador  :   std_logic_vector(1 downto 0) := "00";
  signal  input4    :   std_logic_vector(4 downto 0) := "00000";
  begin

  segs: process (clk, rst)
    begin
      if rst = '1' then
        contador  <= "00";
        seg       <= "000";
      elsif clk = '1' and clk'event then
        if en = '1' then
          case contador is
            when "00" =>
              seg       <= "000";
              input4    <= "XXXXX";
              contador  <= "01";
            when "01" =>
              seg       <= "001";
              input4    <= input1;
              contador  <= "10";
            when "10" =>
              seg       <= "010";
              input4    <= input2;
              contador  <= "11";
            when "11" =>
              seg       <= "100";
              input4    <= input3;
              contador  <= "01";
            when others   =>
              seg  <= "XXX";
            end case;
        else
          seg       <= "000";
          contador  <= "00";
        end if;
      end if;
  end process segs;

  leds: process (clk, rst)
    begin
      if rst = '1' then
        led <= "11111111";
      elsif clk = '1' and clk'event then
        if en = '1' then
          case input4 is
            when "00000" =>  led <= "00000011";
            when "00001" =>  led <= "10011111";
            when "00010" =>  led <= "00100101";
            when "00011" =>  led <= "00001101";
            when "00100" =>  led <= "10011001";
            when "00101" =>  led <= "01001001";
            when "00110" =>  led <= "01000001";
            when "00111" =>  led <= "00011111";
            when "01000" =>  led <= "00000001";
            when "01001" =>  led <= "00001001";
            when "01010" =>  led <= "00010001";
            when "01011" =>  led <= "11000001";
            when "01100" =>  led <= "01100011";
            when "01101" =>  led <= "10000101";
            when "01110" =>  led <= "01100001";
            when "01111" =>  led <= "01110001";
            when "10000" =>  led <= "00000010";
            when "10001" =>  led <= "10011110";
            when "10010" =>  led <= "00100100";
            when "10011" =>  led <= "00001100";
            when "10100" =>  led <= "10011000";
            when "10101" =>  led <= "01001000";
            when "10110" =>  led <= "01000000";
            when "10111" =>  led <= "00011110";
            when "11000" =>  led <= "00000000";
            when "11001" =>  led <= "00001000";
            when "11010" =>  led <= "00010000";
            when "11011" =>  led <= "11000000";
            when "11100" =>  led <= "01100010";
            when "11101" =>  led <= "10000100";
            when "11110" =>  led <= "01100000";
            when "11111" =>  led <= "01110000";
            when others  =>  led <= "XXXXXXXX";
          end case;
        else
          led <= "11111111";
        end if;
      end if;
    end process leds;

end architecture;

project/sim/display_tb.vhdl
library ieee;
use ieee.std_logic_1164.all;
use ieee.numeric_std.all;

entity display_tb is
end entity;

architecture test of display_tb is
  signal s_clk      : std_logic := '0';
  signal s_rst      : std_logic := '0';
  signal s_en       : std_logic := '0';
  signal s_input1   : std_logic_vector(4 downto 0) := "00000";
  signal s_input2   : std_logic_vector(4 downto 0) := "00000";
  signal s_input3   : std_logic_vector(4 downto 0) := "00000";
  signal s_seg      : std_logic_vector(2 downto 0) := "000";
  signal s_led      : std_logic_vector(7 downto 0) := "00000000";
  constant T_CLK    : time := 5 ns;
  begin
  dut : entity work.display
    port map
    (
      clk     => s_clk,
      rst     => s_rst,
      en      => s_en,
      input1  => s_input1,
      input2  => s_input2,
      input3  => s_input3
    );
  s_clk <= not s_clk after T_CLK;
  test: process 
    begin
      s_rst <= '0';
      s_en  <= '0';
      s_input1 <= "00000";
      s_input2 <= "00000";
      s_input3 <= "00000";
      wait for T_CLK;
      s_rst <= '0';
      s_en  <= '1';
      for i in 0 to 15 loop
        s_input1 <= std_logic_vector(to_unsigned(i, 5));
        wait for T_CLK;
      end loop;
      for i in 0 to 15 loop
        s_input2 <= std_logic_vector(to_unsigned(i, 5));
        wait for T_CLK;
      end loop;
      for i in 0 to 15 loop
        s_input3 <= std_logic_vector(to_unsigned(i, 5));
        wait for T_CLK;
      end loop;
      s_rst <= '1';
      s_en  <= '0';
      wait for T_CLK;
      wait;

  end process test;
end architecture;

project/wave/wave.vcd
$date
  Mon Aug 11 01:17:08 2025
$end
$version
  GHDL v0
$end
$timescale
  1 fs
$end
$scope module standard $end
$upscope $end
$scope module std_logic_1164 $end
$upscope $end
$scope module numeric_std $end
$upscope $end
$scope module display_tb $end
$var reg 1 ! s_clk $end
$var reg 1 " s_rst $end
$var reg 1 # s_en $end
$var reg 5 $ s_input1[4:0] $end
$var reg 5 % s_input2[4:0] $end
$var reg 5 & s_input3[4:0] $end
$var reg 3 ' s_seg[2:0] $end
$var reg 8 ( s_led[7:0] $end
$scope module dut $end
$var reg 1 ) clk $end
$var reg 1 * rst $end
$var reg 1 + en $end
$var reg 5 , input1[4:0] $end
$var reg 5 - input2[4:0] $end
$var reg 5 . input3[4:0] $end
$var reg 3 / seg[2:0] $end
$var reg 8 0 led[7:0] $end
$var reg 2 1 contador[1:0] $end
$var reg 5 2 input4[4:0] $end
$upscope $end
$upscope $end
$enddefinitions $end
#0
0!
0"
0#
b00000 $
b00000 %
b00000 &
b000 '
b00000000 (
0)
0*
0+
b00000 ,
b00000 -
b00000 .
bUUU /
bUUUUUUUU 0
b00 1
b00000 2
#5000000
1!
1#
1)
1+
b000 /
b11111111 0
#10000000
0!
b00001 $
0)
b00001 ,
#15000000
1!
b00010 $
1)
b00010 ,
b00000011 0
b01 1
bXXXXX 2
#20000000
0!
b00011 $
0)
b00011 ,
#25000000
1!
b00100 $
1)
b00100 ,
b001 /
bXXXXXXXX 0
b10 1
b00011 2
#30000000
0!
b00101 $
0)
b00101 ,
#35000000
1!
b00110 $
1)
b00110 ,
b010 /
b00001101 0
b11 1
b00000 2
#40000000
0!
b00111 $
0)
b00111 ,
#45000000
1!
b01000 $
1)
b01000 ,
b100 /
b00000011 0
b01 1
#50000000
0!
b01001 $
0)
b01001 ,
#55000000
1!
b01010 $
1)
b01010 ,
b001 /
b10 1
b01001 2
#60000000
0!
b01011 $
0)
b01011 ,
#65000000
1!
b01100 $
1)
b01100 ,
b010 /
b00001001 0
b11 1
b00000 2
#70000000
0!
b01101 $
0)
b01101 ,
#75000000
1!
b01110 $
1)
b01110 ,
b100 /
b00000011 0
b01 1
#80000000
0!
b01111 $
0)
b01111 ,
#85000000
1!
1)
b001 /
b10 1
b01111 2
#90000000
0!
b00001 %
0)
b00001 -
#95000000
1!
b00010 %
1)
b00010 -
b010 /
b01110001 0
b11 1
b00001 2
#100000000
0!
b00011 %
0)
b00011 -
#105000000
1!
b00100 %
1)
b00100 -
b100 /
b10011111 0
b01 1
b00000 2
#110000000
0!
b00101 %
0)
b00101 -
#115000000
1!
b00110 %
1)
b00110 -
b001 /
b00000011 0
b10 1
b01111 2
#120000000
0!
b00111 %
0)
b00111 -
#125000000
1!
b01000 %
1)
b01000 -
b010 /
b01110001 0
b11 1
b00111 2
#130000000
0!
b01001 %
0)
b01001 -
#135000000
1!
b01010 %
1)
b01010 -
b100 /
b00011111 0
b01 1
b00000 2
#140000000
0!
b01011 %
0)
b01011 -
#145000000
1!
b01100 %
1)
b01100 -
b001 /
b00000011 0
b10 1
b01111 2
#150000000
0!
b01101 %
0)
b01101 -
#155000000
1!
b01110 %
1)
b01110 -
b010 /
b01110001 0
b11 1
b01101 2
#160000000
0!
b01111 %
0)
b01111 -
#165000000
1!
1)
b100 /
b10000101 0
b01 1
b00000 2
#170000000
0!
b00001 &
0)
b00001 .
#175000000
1!
b00010 &
1)
b00010 .
b001 /
b00000011 0
b10 1
b01111 2
#180000000
0!
b00011 &
0)
b00011 .
#185000000
1!
b00100 &
1)
b00100 .
b010 /
b01110001 0
b11 1
#190000000
0!
b00101 &
0)
b00101 .
#195000000
1!
b00110 &
1)
b00110 .
b100 /
b01 1
b00101 2
#200000000
0!
b00111 &
0)
b00111 .
#205000000
1!
b01000 &
1)
b01000 .
b001 /
b01001001 0
b10 1
b01111 2
#210000000
0!
b01001 &
0)
b01001 .
#215000000
1!
b01010 &
1)
b01010 .
b010 /
b01110001 0
b11 1
#220000000
0!
b01011 &
0)
b01011 .
#225000000
1!
b01100 &
1)
b01100 .
b100 /
b01 1
b01011 2
#230000000
0!
b01101 &
0)
b01101 .
#235000000
1!
b01110 &
1)
b01110 .
b001 /
b11000001 0
b10 1
b01111 2
#240000000
0!
b01111 &
0)
b01111 .
#245000000
1!
1"
0#
1)
1*
0+
b000 /
b11111111 0
b00 1
