project/src/display.vhdl
library ieee;
use ieee.std_logic_1164.all;
use ieee.numeric_std.all;

entity display is
  port  (
        clk     :   in    std_logic;
        rst_n   :   in    std_logic;
        input1  :   in    std_logic_vector(4 downto 0);
        input2  :   in    std_logic_vector(4 downto 0);
        input3  :   in    std_logic_vector(4 downto 0);
        input4  :   in    std_logic_vector(4 downto 0);
        input5  :   in    std_logic_vector(4 downto 0);
        input6  :   in    std_logic_vector(4 downto 0);
        input7  :   in    std_logic_vector(4 downto 0);
        input8  :   in    std_logic_vector(4 downto 0);
        seg     :   out   std_logic_vector(7 downto 0);
        led     :   out   std_logic_vector(7 downto 0)
        );
end entity;

architecture rtl of display is

  signal contador   :   integer range 0 to 7         := 0;
  signal inputs    :   std_logic_vector(4 downto 0) := (others => '0');
  begin
        
  segs: process (clk, rst_n)
    begin
      if rst_n = '0' then
        contador  <= 0;
        seg       <= (others => '0');
        inputs   <= (others => '0');
      elsif rising_edge(clk) then
        case contador is
          when 0 =>
            seg       <= "00000001";
            inputs   <= input1;
            contador  <= 1;
          when 1 =>
            seg       <= "00000010";
            inputs   <= input2;
            contador  <= 2;
          when 2 =>
            seg       <= "00000100";
            inputs   <= input3;
            contador  <= 3;
          when 3 =>
            seg       <= "00001000";
            inputs   <= input4;
            contador  <= 4;
          when 4 =>
            seg       <= "00010000";
            inputs   <= input5;
            contador  <= 5;
          when 5 =>
            seg       <= "00100000";
            inputs   <= input6;
            contador  <= 6;
          when 6 =>
            seg       <= "01000000";
            inputs   <= input7;
            contador  <= 7;
          when 7 =>
            seg       <= "10000000";
            inputs   <= input8;
            contador  <= 0;
          when others => seg  <= (others => 'X');
        end case;
      end if;
  end process segs;

  leds: process (clk, rst_n)
    begin
      if rst_n = '0' then
        led <= (others => '1');
      elsif rising_edge(clk) then
        case inputs is
          when "00000" =>  led <= "11000000";
          when "00001" =>  led <= "11111001";
          when "00010" =>  led <= "10100100";
          when "00011" =>  led <= "10110000";
          when "00100" =>  led <= "10011001";
          when "00101" =>  led <= "10010010";
          when "00110" =>  led <= "10000010";
          when "00111" =>  led <= "11111000";
          when "01000" =>  led <= "10000000";
          when "01001" =>  led <= "10011000";
          when "01010" =>  led <= "10001000";
          when "01011" =>  led <= "10000011";
          when "01100" =>  led <= "10100111";
          when "01101" =>  led <= "10100001";
          when "01110" =>  led <= "10000110";
          when "01111" =>  led <= "10001110";
          when "10000" =>  led <= "01000000";
          when "10001" =>  led <= "01111001";
          when "10010" =>  led <= "00100100";
          when "10011" =>  led <= "00110000";
          when "10100" =>  led <= "00011001";
          when "10101" =>  led <= "00010010";
          when "10110" =>  led <= "00000010";
          when "10111" =>  led <= "01111000";
          when "11000" =>  led <= "00000000";
          when "11001" =>  led <= "00011000";
          when "11010" =>  led <= "00001000";
          when "11011" =>  led <= "00000011";
          when "11100" =>  led <= "00100111";
          when "11101" =>  led <= "00100001";
          when "11110" =>  led <= "00000110";
          when "11111" =>  led <= "00001110";
          when others  =>  led <= (others => 'X');
        end case;
      end if;
    end process leds;

end architecture;

project/sim/display_tb.vhdl
library ieee;
use ieee.std_logic_1164.all;
use ieee.numeric_std.all;
use std.env.all;

entity display_tb is
end entity;

architecture test of display_tb is
  signal s_clk      : std_logic := '0';
  signal s_rst_n    : std_logic := '0';
  signal s_input1   : std_logic_vector(4 downto 0) := "00000";
  signal s_input2   : std_logic_vector(4 downto 0) := "00000";
  signal s_input3   : std_logic_vector(4 downto 0) := "00000";
  signal s_input4   : std_logic_vector(4 downto 0) := "00000";
  signal s_input5   : std_logic_vector(4 downto 0) := "00000";
  signal s_input6   : std_logic_vector(4 downto 0) := "00000";
  signal s_input7   : std_logic_vector(4 downto 0) := "00000";
  signal s_input8   : std_logic_vector(4 downto 0) := "00000";
  signal s_seg      : std_logic_vector(7 downto 0) := "00000000";
  signal s_led      : std_logic_vector(7 downto 0) := "00000000";
  constant T_CLK    : time := 20 ns;
  constant T_DLY    : time := 100 ns;
  begin
  dut : entity work.display
    port map
    (
      clk     => s_clk,
      rst_n   => s_rst_n,
      input1  => s_input1,
      input2  => s_input2,
      input3  => s_input3,
      input4  => s_input4,
      input5  => s_input5,
      input6  => s_input6,
      input7  => s_input7,
      input8  => s_input8,
      seg     => s_seg,
      led     => s_led
    );
  s_clk <= not s_clk after T_CLK;
  process 
    begin
      s_rst_n  <= '0';
      wait for T_DLY;
      s_rst_n  <= '1';
      wait for T_DLY;
      for i in 0 to 31 loop
        s_input1 <= std_logic_vector(to_unsigned(i, 5));
        wait for T_DLY;
      end loop;
      for i in 0 to 31 loop
        s_input2 <= std_logic_vector(to_unsigned(i, 5));
        wait for T_DLY;
      end loop;
      for i in 0 to 31 loop
        s_input3 <= std_logic_vector(to_unsigned(i, 5));
        wait for T_DLY;
      end loop;
      for i in 0 to 31 loop
        s_input4 <= std_logic_vector(to_unsigned(i, 5));
        wait for T_DLY;
      end loop;
      for i in 0 to 31 loop
        s_input5 <= std_logic_vector(to_unsigned(i, 5));
        wait for T_DLY;
      end loop;
      for i in 0 to 31 loop
        s_input6 <= std_logic_vector(to_unsigned(i, 5));
        wait for T_DLY;
      end loop;
      for i in 0 to 31 loop
        s_input7 <= std_logic_vector(to_unsigned(i, 5));
        wait for T_DLY;
      end loop;
      for i in 0 to 31 loop
        s_input8 <= std_logic_vector(to_unsigned(i, 5));
        wait for T_DLY;
      end loop;
      s_rst_n <= '0';
      wait for 2*T_DLY;

      assert false
        report "Simulación terminada"
        severity note;
        stop;

  end process;
end architecture;

project/wave/wave.vcd
$date
  Wed Aug 13 18:23:17 2025
$end
$version
  GHDL v0
$end
$timescale
  1 fs
$end
$scope module standard $end
$upscope $end
$scope module textio $end
$upscope $end
$scope module std_logic_1164 $end
$upscope $end
$scope module numeric_std $end
$upscope $end
$scope module env $end
$upscope $end
$scope module display_tb $end
$var reg 1 ! s_clk $end
$var reg 1 " s_rst_n $end
$var reg 5 # s_input1[4:0] $end
$var reg 5 $ s_input2[4:0] $end
$var reg 5 % s_input3[4:0] $end
$var reg 5 & s_input4[4:0] $end
$var reg 5 ' s_input5[4:0] $end
$var reg 5 ( s_input6[4:0] $end
$var reg 5 ) s_input7[4:0] $end
$var reg 5 * s_input8[4:0] $end
$var reg 8 + s_seg[7:0] $end
$var reg 8 , s_led[7:0] $end
$scope module dut $end
$var reg 1 - clk $end
$var reg 1 . rst_n $end
$var reg 5 / input1[4:0] $end
$var reg 5 0 input2[4:0] $end
$var reg 5 1 input3[4:0] $end
$var reg 5 2 input4[4:0] $end
$var reg 5 3 input5[4:0] $end
$var reg 5 4 input6[4:0] $end
$var reg 5 5 input7[4:0] $end
$var reg 5 6 input8[4:0] $end
$var reg 8 7 seg[7:0] $end
$var reg 8 8 led[7:0] $end
$var integer 32 9 contador $end
$var reg 5 : inputs[4:0] $end
$upscope $end
$upscope $end
$enddefinitions $end
#0
0!
0"
b00000 #
b00000 $
b00000 %
b00000 &
b00000 '
b00000 (
b00000 )
b00000 *
b00000000 +
b11111111 ,
0-
0.
b00000 /
b00000 0
b00000 1
b00000 2
b00000 3
b00000 4
b00000 5
b00000 6
b00000000 7
b11111111 8
b0 9
b00000 :
#20000000
1!
1-
#40000000
0!
0-
#60000000
1!
1-
#80000000
0!
0-
#100000000
1!
1"
1-
1.
#120000000
0!
0-
#140000000
1!
b00000001 +
b11000000 ,
1-
b00000001 7
b11000000 8
b1 9
#160000000
0!
0-
#180000000
1!
b00000010 +
1-
b00000010 7
b10 9
#200000000
0!
0-
#220000000
1!
b00000100 +
1-
b00000100 7
b11 9
#240000000
0!
0-
#260000000
1!
b00001000 +
1-
b00001000 7
b100 9
#280000000
0!
0-
#300000000
1!
b00001 #
b00010000 +
1-
b00001 /
b00010000 7
b101 9
#320000000
0!
0-
#340000000
1!
b00100000 +
1-
b00100000 7
b110 9
#360000000
0!
0-
#380000000
1!
b01000000 +
1-
b01000000 7
b111 9
#400000000
0!
b00010 #
0-
b00010 /
#420000000
1!
b10000000 +
1-
b10000000 7
b0 9
#440000000
0!
0-
#460000000
1!
b00000001 +
1-
b00000001 7
b1 9
b00010 :
#480000000
0!
0-
#500000000
1!
b00011 #
b00000010 +
b10100100 ,
1-
b00011 /
b00000010 7
b10100100 8
b10 9
b00000 :
#520000000
0!
0-
#540000000
1!
b00000100 +
b11000000 ,
1-
b00000100 7
b11000000 8
b11 9
#560000000
0!
0-
#580000000
1!
b00001000 +
1-
b00001000 7
b100 9
#600000000
0!
b00100 #
0-
b00100 /
#620000000
1!
b00010000 +
1-
b00010000 7
b101 9
#640000000
0!
0-
#660000000
1!
b00100000 +
1-
b00100000 7
b110 9
#680000000
0!
0-
#700000000
1!
b00101 #
b01000000 +
1-
b00101 /
b01000000 7
b111 9
#720000000
0!
0-
#740000000
1!
b10000000 +
1-
b10000000 7
b0 9
#760000000
0!
0-
#780000000
1!
b00000001 +
1-
b00000001 7
b1 9
b00101 :
#800000000
0!
b00110 #
0-
b00110 /
#820000000
1!
b00000010 +
b10010010 ,
1-
b00000010 7
b10010010 8
b10 9
b00000 :
#840000000
0!
0-
#860000000
1!
b00000100 +
b11000000 ,
1-
b00000100 7
b11000000 8
b11 9
#880000000
0!
0-
#900000000
1!
b00111 #
b00001000 +
1-
b00111 /
b00001000 7
b100 9
#920000000
0!
0-
#940000000
1!
b00010000 +
1-
b00010000 7
b101 9
#960000000
0!
0-
#980000000
1!
b00100000 +
1-
b00100000 7
b110 9
#1000000000
0!
b01000 #
0-
b01000 /
#1020000000
1!
b01000000 +
1-
b01000000 7
b111 9
#1040000000
0!
0-
#1060000000
1!
b10000000 +
1-
b10000000 7
b0 9
#1080000000
0!
0-
#1100000000
1!
b01001 #
b00000001 +
1-
b01001 /
b00000001 7
b1 9
b01000 :
#1120000000
0!
0-
#1140000000
1!
b00000010 +
b10000000 ,
1-
b00000010 7
b10000000 8
b10 9
b00000 :
#1160000000
0!
0-
#1180000000
1!
b00000100 +
b11000000 ,
1-
b00000100 7
b11000000 8
b11 9
#1200000000
0!
b01010 #
0-
b01010 /
#1220000000
1!
b00001000 +
1-
b00001000 7
b100 9
#1240000000
0!
0-
#1260000000
1!
b00010000 +
1-
b00010000 7
b101 9
#1280000000
0!
0-
#1300000000
1!
b01011 #
b00100000 +
1-
b01011 /
b00100000 7
b110 9
#1320000000
0!
0-
#1340000000
1!
b01000000 +
1-
b01000000 7
b111 9
#1360000000
0!
0-
#1380000000
1!
b10000000 +
1-
b10000000 7
b0 9
#1400000000
0!
b01100 #
0-
b01100 /
#1420000000
1!
b00000001 +
1-
b00000001 7
b1 9
b01100 :
#1440000000
0!
0-
#1460000000
1!
b00000010 +
b10100111 ,
1-
b00000010 7
b10100111 8
b10 9
b00000 :
#1480000000
0!
0-
#1500000000
1!
b01101 #
b00000100 +
b11000000 ,
1-
b01101 /
b00000100 7
b11000000 8
b11 9
#1520000000
0!
0-
#1540000000
1!
b00001000 +
1-
b00001000 7
b100 9
#1560000000
0!
0-
#1580000000
1!
b00010000 +
1-
b00010000 7
b101 9
#1600000000
0!
b01110 #
0-
b01110 /
#1620000000
1!
b00100000 +
1-
b00100000 7
b110 9
#1640000000
0!
0-
#1660000000
1!
b01000000 +
1-
b01000000 7
b111 9
#1680000000
0!
0-
#1700000000
1!
b01111 #
b10000000 +
1-
b01111 /
b10000000 7
b0 9
#1720000000
0!
0-
#1740000000
1!
b00000001 +
1-
b00000001 7
b1 9
b01111 :
#1760000000
0!
0-
#1780000000
1!
b00000010 +
b10001110 ,
1-
b00000010 7
b10001110 8
b10 9
b00000 :
#1800000000
0!
b10000 #
0-
b10000 /
#1820000000
1!
b00000100 +
b11000000 ,
1-
b00000100 7
b11000000 8
b11 9
#1840000000
0!
0-
#1860000000
1!
b00001000 +
1-
b00001000 7
b100 9
#1880000000
0!
0-
#1900000000
1!
b10001 #
b00010000 +
1-
b10001 /
b00010000 7
b101 9
#1920000000
0!
0-
#1940000000
1!
b00100000 +
1-
b00100000 7
b110 9
#1960000000
0!
0-
#1980000000
1!
b01000000 +
1-
b01000000 7
b111 9
#2000000000
0!
b10010 #
0-
b10010 /
#2020000000
1!
b10000000 +
1-
b10000000 7
b0 9
#2040000000
0!
0-
#2060000000
1!
b00000001 +
1-
b00000001 7
b1 9
b10010 :
#2080000000
0!
0-
#2100000000
1!
b10011 #
b00000010 +
b00100100 ,
1-
b10011 /
b00000010 7
b00100100 8
b10 9
b00000 :
#2120000000
0!
0-
#2140000000
1!
b00000100 +
b11000000 ,
1-
b00000100 7
b11000000 8
b11 9
#2160000000
0!
0-
#2180000000
1!
b00001000 +
1-
b00001000 7
b100 9
#2200000000
0!
b10100 #
0-
b10100 /
#2220000000
1!
b00010000 +
1-
b00010000 7
b101 9
#2240000000
0!
0-
#2260000000
1!
b00100000 +
1-
b00100000 7
b110 9
#2280000000
0!
0-
#2300000000
1!
b10101 #
b01000000 +
1-
b10101 /
b01000000 7
b111 9
#2320000000
0!
0-
#2340000000
1!
b10000000 +
1-
b10000000 7
b0 9
#2360000000
0!
0-
#2380000000
1!
b00000001 +
1-
b00000001 7
b1 9
b10101 :
#2400000000
0!
b10110 #
0-
b10110 /
#2420000000
1!
b00000010 +
b00010010 ,
1-
b00000010 7
b00010010 8
b10 9
b00000 :
#2440000000
0!
0-
#2460000000
1!
b00000100 +
b11000000 ,
1-
b00000100 7
b11000000 8
b11 9
#2480000000
0!
0-
#2500000000
1!
b10111 #
b00001000 +
1-
b10111 /
b00001000 7
b100 9
#2520000000
0!
0-
#2540000000
1!
b00010000 +
1-
b00010000 7
b101 9
#2560000000
0!
0-
#2580000000
1!
b00100000 +
1-
b00100000 7
b110 9
#2600000000
0!
b11000 #
0-
b11000 /
#2620000000
1!
b01000000 +
1-
b01000000 7
b111 9
#2640000000
0!
0-
#2660000000
1!
b10000000 +
1-
b10000000 7
b0 9
#2680000000
0!
0-
#2700000000
1!
b11001 #
b00000001 +
1-
b11001 /
b00000001 7
b1 9
b11000 :
#2720000000
0!
0-
#2740000000
1!
b00000010 +
b00000000 ,
1-
b00000010 7
b00000000 8
b10 9
b00000 :
#2760000000
0!
0-
#2780000000
1!
b00000100 +
b11000000 ,
1-
b00000100 7
b11000000 8
b11 9
#2800000000
0!
b11010 #
0-
b11010 /
#2820000000
1!
b00001000 +
1-
b00001000 7
b100 9
#2840000000
0!
0-
#2860000000
1!
b00010000 +
1-
b00010000 7
b101 9
#2880000000
0!
0-
#2900000000
1!
b11011 #
b00100000 +
1-
b11011 /
b00100000 7
b110 9
#2920000000
0!
0-
#2940000000
1!
b01000000 +
1-
b01000000 7
b111 9
#2960000000
0!
0-
#2980000000
1!
b10000000 +
1-
b10000000 7
b0 9
#3000000000
0!
b11100 #
0-
b11100 /
#3020000000
1!
b00000001 +
1-
b00000001 7
b1 9
b11100 :
#3040000000
0!
0-
#3060000000
1!
b00000010 +
b00100111 ,
1-
b00000010 7
b00100111 8
b10 9
b00000 :
#3080000000
0!
0-
#3100000000
1!
b11101 #
b00000100 +
b11000000 ,
1-
b11101 /
b00000100 7
b11000000 8
b11 9
#3120000000
0!
0-
#3140000000
1!
b00001000 +
1-
b00001000 7
b100 9
#3160000000
0!
0-
#3180000000
1!
b00010000 +
1-
b00010000 7
b101 9
#3200000000
0!
b11110 #
0-
b11110 /
#3220000000
1!
b00100000 +
1-
b00100000 7
b110 9
#3240000000
0!
0-
#3260000000
1!
b01000000 +
1-
b01000000 7
b111 9
#3280000000
0!
0-
#3300000000
1!
b11111 #
b10000000 +
1-
b11111 /
b10000000 7
b0 9
#3320000000
0!
0-
#3340000000
1!
b00000001 +
1-
b00000001 7
b1 9
b11111 :
#3360000000
0!
0-
#3380000000
1!
b00000010 +
b00001110 ,
1-
b00000010 7
b00001110 8
b10 9
b00000 :
#3400000000
0!
0-
#3420000000
1!
b00000100 +
b11000000 ,
1-
b00000100 7
b11000000 8
b11 9
#3440000000
0!
0-
#3460000000
1!
b00001000 +
1-
b00001000 7
b100 9
#3480000000
0!
0-
#3500000000
1!
b00001 $
b00010000 +
1-
b00001 0
b00010000 7
b101 9
#3520000000
0!
0-
#3540000000
1!
b00100000 +
1-
b00100000 7
b110 9
#3560000000
0!
0-
#3580000000
1!
b01000000 +
1-
b01000000 7
b111 9
#3600000000
0!
b00010 $
0-
b00010 0
#3620000000
1!
b10000000 +
1-
b10000000 7
b0 9
#3640000000
0!
0-
#3660000000
1!
b00000001 +
1-
b00000001 7
b1 9
b11111 :
#3680000000
0!
0-
#3700000000
1!
b00011 $
b00000010 +
b00001110 ,
1-
b00011 0
b00000010 7
b00001110 8
b10 9
b00010 :
#3720000000
0!
0-
#3740000000
1!
b00000100 +
b10100100 ,
1-
b00000100 7
b10100100 8
b11 9
b00000 :
#3760000000
0!
0-
#3780000000
1!
b00001000 +
b11000000 ,
1-
b00001000 7
b11000000 8
b100 9
#3800000000
0!
b00100 $
0-
b00100 0
#3820000000
1!
b00010000 +
1-
b00010000 7
b101 9
#3840000000
0!
0-
#3860000000
1!
b00100000 +
1-
b00100000 7
b110 9
#3880000000
0!
0-
#3900000000
1!
b00101 $
b01000000 +
1-
b00101 0
b01000000 7
b111 9
#3920000000
0!
0-
#3940000000
1!
b10000000 +
1-
b10000000 7
b0 9
#3960000000
0!
0-
#3980000000
1!
b00000001 +
1-
b00000001 7
b1 9
b11111 :
#4000000000
0!
b00110 $
0-
b00110 0
#4020000000
1!
b00000010 +
b00001110 ,
1-
b00000010 7
b00001110 8
b10 9
b00110 :
#4040000000
0!
0-
#4060000000
1!
b00000100 +
b10000010 ,
1-
b00000100 7
b10000010 8
b11 9
b00000 :
#4080000000
0!
0-
#4100000000
1!
b00111 $
b00001000 +
b11000000 ,
1-
b00111 0
b00001000 7
b11000000 8
b100 9
#4120000000
0!
0-
#4140000000
1!
b00010000 +
1-
b00010000 7
b101 9
#4160000000
0!
0-
#4180000000
1!
b00100000 +
1-
b00100000 7
b110 9
#4200000000
0!
b01000 $
0-
b01000 0
#4220000000
1!
b01000000 +
1-
b01000000 7
b111 9
#4240000000
0!
0-
#4260000000
1!
b10000000 +
1-
b10000000 7
b0 9
#4280000000
0!
0-
#4300000000
1!
b01001 $
b00000001 +
1-
b01001 0
b00000001 7
b1 9
b11111 :
#4320000000
0!
0-
#4340000000
1!
b00000010 +
b00001110 ,
1-
b00000010 7
b00001110 8
b10 9
b01001 :
#4360000000
0!
0-
#4380000000
1!
b00000100 +
b10011000 ,
1-
b00000100 7
b10011000 8
b11 9
b00000 :
#4400000000
0!
b01010 $
0-
b01010 0
#4420000000
1!
b00001000 +
b11000000 ,
1-
b00001000 7
b11000000 8
b100 9
#4440000000
0!
0-
#4460000000
1!
b00010000 +
1-
b00010000 7
b101 9
#4480000000
0!
0-
#4500000000
1!
b01011 $
b00100000 +
1-
b01011 0
b00100000 7
b110 9
#4520000000
0!
0-
#4540000000
1!
b01000000 +
1-
b01000000 7
b111 9
#4560000000
0!
0-
#4580000000
1!
b10000000 +
1-
b10000000 7
b0 9
#4600000000
0!
b01100 $
0-
b01100 0
#4620000000
1!
b00000001 +
1-
b00000001 7
b1 9
b11111 :
#4640000000
0!
0-
#4660000000
1!
b00000010 +
b00001110 ,
1-
b00000010 7
b00001110 8
b10 9
b01100 :
#4680000000
0!
0-
#4700000000
1!
b01101 $
b00000100 +
b10100111 ,
1-
b01101 0
b00000100 7
b10100111 8
b11 9
b00000 :
#4720000000
0!
0-
#4740000000
1!
b00001000 +
b11000000 ,
1-
b00001000 7
b11000000 8
b100 9
#4760000000
0!
0-
#4780000000
1!
b00010000 +
1-
b00010000 7
b101 9
#4800000000
0!
b01110 $
0-
b01110 0
#4820000000
1!
b00100000 +
1-
b00100000 7
b110 9
#4840000000
0!
0-
#4860000000
1!
b01000000 +
1-
b01000000 7
b111 9
#4880000000
0!
0-
#4900000000
1!
b01111 $
b10000000 +
1-
b01111 0
b10000000 7
b0 9
#4920000000
0!
0-
#4940000000
1!
b00000001 +
1-
b00000001 7
b1 9
b11111 :
#4960000000
0!
0-
#4980000000
1!
b00000010 +
b00001110 ,
1-
b00000010 7
b00001110 8
b10 9
b01111 :
#5000000000
0!
b10000 $
0-
b10000 0
#5020000000
1!
b00000100 +
b10001110 ,
1-
b00000100 7
b10001110 8
b11 9
b00000 :
#5040000000
0!
0-
#5060000000
1!
b00001000 +
b11000000 ,
1-
b00001000 7
b11000000 8
b100 9
#5080000000
0!
0-
#5100000000
1!
b10001 $
b00010000 +
1-
b10001 0
b00010000 7
b101 9
#5120000000
0!
0-
#5140000000
1!
b00100000 +
1-
b00100000 7
b110 9
#5160000000
0!
0-
#5180000000
1!
b01000000 +
1-
b01000000 7
b111 9
#5200000000
0!
b10010 $
0-
b10010 0
#5220000000
1!
b10000000 +
1-
b10000000 7
b0 9
#5240000000
0!
0-
#5260000000
1!
b00000001 +
1-
b00000001 7
b1 9
b11111 :
#5280000000
0!
0-
#5300000000
1!
b10011 $
b00000010 +
b00001110 ,
1-
b10011 0
b00000010 7
b00001110 8
b10 9
b10010 :
#5320000000
0!
0-
#5340000000
1!
b00000100 +
b00100100 ,
1-
b00000100 7
b00100100 8
b11 9
b00000 :
#5360000000
0!
0-
#5380000000
1!
b00001000 +
b11000000 ,
1-
b00001000 7
b11000000 8
b100 9
#5400000000
0!
b10100 $
0-
b10100 0
#5420000000
1!
b00010000 +
1-
b00010000 7
b101 9
#5440000000
0!
0-
#5460000000
1!
b00100000 +
1-
b00100000 7
b110 9
#5480000000
0!
0-
#5500000000
1!
b10101 $
b01000000 +
1-
b10101 0
b01000000 7
b111 9
#5520000000
0!
0-
#5540000000
1!
b10000000 +
1-
b10000000 7
b0 9
#5560000000
0!
0-
#5580000000
1!
b00000001 +
1-
b00000001 7
b1 9
b11111 :
#5600000000
0!
b10110 $
0-
b10110 0
#5620000000
1!
b00000010 +
b00001110 ,
1-
b00000010 7
b00001110 8
b10 9
b10110 :
#5640000000
0!
0-
#5660000000
1!
b00000100 +
b00000010 ,
1-
b00000100 7
b00000010 8
b11 9
b00000 :
#5680000000
0!
0-
#5700000000
1!
b10111 $
b00001000 +
b11000000 ,
1-
b10111 0
b00001000 7
b11000000 8
b100 9
#5720000000
0!
0-
#5740000000
1!
b00010000 +
1-
b00010000 7
b101 9
#5760000000
0!
0-
#5780000000
1!
b00100000 +
1-
b00100000 7
b110 9
#5800000000
0!
b11000 $
0-
b11000 0
#5820000000
1!
b01000000 +
1-
b01000000 7
b111 9
#5840000000
0!
0-
#5860000000
1!
b10000000 +
1-
b10000000 7
b0 9
#5880000000
0!
0-
#5900000000
1!
b11001 $
b00000001 +
1-
b11001 0
b00000001 7
b1 9
b11111 :
#5920000000
0!
0-
#5940000000
1!
b00000010 +
b00001110 ,
1-
b00000010 7
b00001110 8
b10 9
b11001 :
#5960000000
0!
0-
#5980000000
1!
b00000100 +
b00011000 ,
1-
b00000100 7
b00011000 8
b11 9
b00000 :
#6000000000
0!
b11010 $
0-
b11010 0
#6020000000
1!
b00001000 +
b11000000 ,
1-
b00001000 7
b11000000 8
b100 9
#6040000000
0!
0-
#6060000000
1!
b00010000 +
1-
b00010000 7
b101 9
#6080000000
0!
0-
#6100000000
1!
b11011 $
b00100000 +
1-
b11011 0
b00100000 7
b110 9
#6120000000
0!
0-
#6140000000
1!
b01000000 +
1-
b01000000 7
b111 9
#6160000000
0!
0-
#6180000000
1!
b10000000 +
1-
b10000000 7
b0 9
#6200000000
0!
b11100 $
0-
b11100 0
#6220000000
1!
b00000001 +
1-
b00000001 7
b1 9
b11111 :
#6240000000
0!
0-
#6260000000
1!
b00000010 +
b00001110 ,
1-
b00000010 7
b00001110 8
b10 9
b11100 :
#6280000000
0!
0-
#6300000000
1!
b11101 $
b00000100 +
b00100111 ,
1-
b11101 0
b00000100 7
b00100111 8
b11 9
b00000 :
#6320000000
0!
0-
#6340000000
1!
b00001000 +
b11000000 ,
1-
b00001000 7
b11000000 8
b100 9
#6360000000
0!
0-
#6380000000
1!
b00010000 +
1-
b00010000 7
b101 9
#6400000000
0!
b11110 $
0-
b11110 0
#6420000000
1!
b00100000 +
1-
b00100000 7
b110 9
#6440000000
0!
0-
#6460000000
1!
b01000000 +
1-
b01000000 7
b111 9
#6480000000
0!
0-
#6500000000
1!
b11111 $
b10000000 +
1-
b11111 0
b10000000 7
b0 9
#6520000000
0!
0-
#6540000000
1!
b00000001 +
1-
b00000001 7
b1 9
b11111 :
#6560000000
0!
0-
#6580000000
1!
b00000010 +
b00001110 ,
1-
b00000010 7
b00001110 8
b10 9
#6600000000
0!
0-
#6620000000
1!
b00000100 +
1-
b00000100 7
b11 9
b00000 :
#6640000000
0!
0-
#6660000000
1!
b00001000 +
b11000000 ,
1-
b00001000 7
b11000000 8
b100 9
#6680000000
0!
0-
#6700000000
1!
b00001 %
b00010000 +
1-
b00001 1
b00010000 7
b101 9
#6720000000
0!
0-
#6740000000
1!
b00100000 +
1-
b00100000 7
b110 9
#6760000000
0!
0-
#6780000000
1!
b01000000 +
1-
b01000000 7
b111 9
#6800000000
0!
b00010 %
0-
b00010 1
#6820000000
1!
b10000000 +
1-
b10000000 7
b0 9
#6840000000
0!
0-
#6860000000
1!
b00000001 +
1-
b00000001 7
b1 9
b11111 :
#6880000000
0!
0-
#6900000000
1!
b00011 %
b00000010 +
b00001110 ,
1-
b00011 1
b00000010 7
b00001110 8
b10 9
#6920000000
0!
0-
#6940000000
1!
b00000100 +
1-
b00000100 7
b11 9
b00011 :
#6960000000
0!
0-
#6980000000
1!
b00001000 +
b10110000 ,
1-
b00001000 7
b10110000 8
b100 9
b00000 :
#7000000000
0!
b00100 %
0-
b00100 1
#7020000000
1!
b00010000 +
b11000000 ,
1-
b00010000 7
b11000000 8
b101 9
#7040000000
0!
0-
#7060000000
1!
b00100000 +
1-
b00100000 7
b110 9
#7080000000
0!
0-
#7100000000
1!
b00101 %
b01000000 +
1-
b00101 1
b01000000 7
b111 9
#7120000000
0!
0-
#7140000000
1!
b10000000 +
1-
b10000000 7
b0 9
#7160000000
0!
0-
#7180000000
1!
b00000001 +
1-
b00000001 7
b1 9
b11111 :
#7200000000
0!
b00110 %
0-
b00110 1
#7220000000
1!
b00000010 +
b00001110 ,
1-
b00000010 7
b00001110 8
b10 9
#7240000000
0!
0-
#7260000000
1!
b00000100 +
1-
b00000100 7
b11 9
b00110 :
#7280000000
0!
0-
#7300000000
1!
b00111 %
b00001000 +
b10000010 ,
1-
b00111 1
b00001000 7
b10000010 8
b100 9
b00000 :
#7320000000
0!
0-
#7340000000
1!
b00010000 +
b11000000 ,
1-
b00010000 7
b11000000 8
b101 9
#7360000000
0!
0-
#7380000000
1!
b00100000 +
1-
b00100000 7
b110 9
#7400000000
0!
b01000 %
0-
b01000 1
#7420000000
1!
b01000000 +
1-
b01000000 7
b111 9
#7440000000
0!
0-
#7460000000
1!
b10000000 +
1-
b10000000 7
b0 9
#7480000000
0!
0-
#7500000000
1!
b01001 %
b00000001 +
1-
b01001 1
b00000001 7
b1 9
b11111 :
#7520000000
0!
0-
#7540000000
1!
b00000010 +
b00001110 ,
1-
b00000010 7
b00001110 8
b10 9
#7560000000
0!
0-
#7580000000
1!
b00000100 +
1-
b00000100 7
b11 9
b01001 :
#7600000000
0!
b01010 %
0-
b01010 1
#7620000000
1!
b00001000 +
b10011000 ,
1-
b00001000 7
b10011000 8
b100 9
b00000 :
#7640000000
0!
0-
#7660000000
1!
b00010000 +
b11000000 ,
1-
b00010000 7
b11000000 8
b101 9
#7680000000
0!
0-
#7700000000
1!
b01011 %
b00100000 +
1-
b01011 1
b00100000 7
b110 9
#7720000000
0!
0-
#7740000000
1!
b01000000 +
1-
b01000000 7
b111 9
#7760000000
0!
0-
#7780000000
1!
b10000000 +
1-
b10000000 7
b0 9
#7800000000
0!
b01100 %
0-
b01100 1
#7820000000
1!
b00000001 +
1-
b00000001 7
b1 9
b11111 :
#7840000000
0!
0-
#7860000000
1!
b00000010 +
b00001110 ,
1-
b00000010 7
b00001110 8
b10 9
#7880000000
0!
0-
#7900000000
1!
b01101 %
b00000100 +
1-
b01101 1
b00000100 7
b11 9
b01100 :
#7920000000
0!
0-
#7940000000
1!
b00001000 +
b10100111 ,
1-
b00001000 7
b10100111 8
b100 9
b00000 :
#7960000000
0!
0-
#7980000000
1!
b00010000 +
b11000000 ,
1-
b00010000 7
b11000000 8
b101 9
#8000000000
0!
b01110 %
0-
b01110 1
#8020000000
1!
b00100000 +
1-
b00100000 7
b110 9
#8040000000
0!
0-
#8060000000
1!
b01000000 +
1-
b01000000 7
b111 9
#8080000000
0!
0-
#8100000000
1!
b01111 %
b10000000 +
1-
b01111 1
b10000000 7
b0 9
#8120000000
0!
0-
#8140000000
1!
b00000001 +
1-
b00000001 7
b1 9
b11111 :
#8160000000
0!
0-
#8180000000
1!
b00000010 +
b00001110 ,
1-
b00000010 7
b00001110 8
b10 9
#8200000000
0!
b10000 %
0-
b10000 1
#8220000000
1!
b00000100 +
1-
b00000100 7
b11 9
b10000 :
#8240000000
0!
0-
#8260000000
1!
b00001000 +
b01000000 ,
1-
b00001000 7
b01000000 8
b100 9
b00000 :
#8280000000
0!
0-
#8300000000
1!
b10001 %
b00010000 +
b11000000 ,
1-
b10001 1
b00010000 7
b11000000 8
b101 9
#8320000000
0!
0-
#8340000000
1!
b00100000 +
1-
b00100000 7
b110 9
#8360000000
0!
0-
#8380000000
1!
b01000000 +
1-
b01000000 7
b111 9
#8400000000
0!
b10010 %
0-
b10010 1
#8420000000
1!
b10000000 +
1-
b10000000 7
b0 9
#8440000000
0!
0-
#8460000000
1!
b00000001 +
1-
b00000001 7
b1 9
b11111 :
#8480000000
0!
0-
