project/src/display.vhdl
library ieee;
use ieee.std_logic_1164.all;
use ieee.numeric_std.all;

entity display is
  port  (
        clk     :   in    std_logic;
        rst     :   in    std_logic;
        en      :   in    std_logic;
        input1  :   in    std_logic_vector(4 downto 0);
        input2  :   in    std_logic_vector(4 downto 0);
        input3  :   in    std_logic_vector(4 downto 0);
        seg     :   out   std_logic_vector(2 downto 0);
        led     :   out   std_logic_vector(7 downto 0)
        );
end entity;

architecture rtl of display is

  signal  contador  :   std_logic_vector(1 downto 0) := (others => '0');
  signal  s_input   :   std_logic_vector(4 downto 0) := (others => '0');
  begin

  segs: process (clk, rst)
    begin
      if rst = '1' then
        contador  <= (others => '0');
        seg       <= (others => '0');
      elsif rising_edge(clk) then
        if en = '1' then
          case contador is
            when "00" =>
              seg       <= "000";
              s_input    <= (others => '0');
              contador  <= "01";
            when "01" =>
              seg       <= "001";
              s_input    <= input1;
              contador  <= "10";
            when "10" =>
              seg       <= "010";
              s_input    <= input2;
              contador  <= "11";
            when "11" =>
              seg       <= "100";
              s_input    <= input3;
              contador  <= "01";
            when others   =>
              seg  <= (others => 'X');
            end case;
        else
          seg       <= (others => '0');
          contador  <= (others => '0');
        end if;
      end if;
  end process segs;

  leds: process (clk, rst)
    begin
      if rst = '1' then
        led <= (others => '1');
      elsif rising_edge(clk) then
        if en = '1' then
          case s_input is
            when "00000" =>  led <= "00000011";
            when "00001" =>  led <= "10011111";
            when "00010" =>  led <= "00100101";
            when "00011" =>  led <= "00001101";
            when "00100" =>  led <= "10011001";
            when "00101" =>  led <= "01001001";
            when "00110" =>  led <= "01000001";
            when "00111" =>  led <= "00011111";
            when "01000" =>  led <= "00000001";
            when "01001" =>  led <= "00001001";
            when "01010" =>  led <= "00010001";
            when "01011" =>  led <= "11000001";
            when "01100" =>  led <= "01100011";
            when "01101" =>  led <= "10000101";
            when "01110" =>  led <= "01100001";
            when "01111" =>  led <= "01110001";
            when "10000" =>  led <= "00000010";
            when "10001" =>  led <= "10011110";
            when "10010" =>  led <= "00100100";
            when "10011" =>  led <= "00001100";
            when "10100" =>  led <= "10011000";
            when "10101" =>  led <= "01001000";
            when "10110" =>  led <= "01000000";
            when "10111" =>  led <= "00011110";
            when "11000" =>  led <= "00000000";
            when "11001" =>  led <= "00001000";
            when "11010" =>  led <= "00010000";
            when "11011" =>  led <= "11000000";
            when "11100" =>  led <= "01100010";
            when "11101" =>  led <= "10000100";
            when "11110" =>  led <= "01100000";
            when "11111" =>  led <= "01110000";
            when others  =>  led <= (others => 'X');
          end case;
        else
          led <= (others => '1');
        end if;
      end if;
    end process leds;

end architecture;

project/sim/display_tb.vhdl
library ieee;
use ieee.std_logic_1164.all;
use ieee.numeric_std.all;
use std.env.all;

entity display_tb is
end entity;

architecture test of display_tb is
  signal s_clk      : std_logic := '0';
  signal s_rst      : std_logic := '0';
  signal s_en       : std_logic := '0';
  signal s_input1   : std_logic_vector(4 downto 0) := "00000";
  signal s_input2   : std_logic_vector(4 downto 0) := "00000";
  signal s_input3   : std_logic_vector(4 downto 0) := "00000";
  signal s_seg      : std_logic_vector(2 downto 0) := "000";
  signal s_led      : std_logic_vector(7 downto 0) := "00000000";
  constant T_CLK    : time := 5 ns;
  constant T_DLY    : time := 20 ns;
  begin
  dut : entity work.display
    port map
    (
      clk     => s_clk,
      rst     => s_rst,
      en      => s_en,
      input1  => s_input1,
      input2  => s_input2,
      input3  => s_input3
    );
  s_clk <= not s_clk after T_CLK;
  process 
    begin
      s_rst <= '1';
      s_en  <= '0';
      s_input1 <= "00000";
      s_input2 <= "00000";
      s_input3 <= "00000";
      wait for T_DLY;
      s_rst <= '0';
      wait for T_DLY;
      s_en  <= '1';
      wait for T_DLY;
      for i in 0 to 15 loop
        s_input1 <= std_logic_vector(to_unsigned(i, 5));
        wait for T_DLY;
      end loop;
      for i in 0 to 15 loop
        s_input2 <= std_logic_vector(to_unsigned(i, 5));
        wait for T_DLY;
      end loop;
      for i in 0 to 15 loop
        s_input3 <= std_logic_vector(to_unsigned(i, 5));
        wait for T_DLY;
      end loop;
      s_rst <= '1';
      s_en  <= '0';
      wait for 2*T_DLY;

      assert false
        report "Simulación terminada"
        severity note;
        stop;

  end process;
end architecture;

project/wave/wave.vcd
$date
  Mon Aug 11 12:23:53 2025
$end
$version
  GHDL v0
$end
$timescale
  1 fs
$end
$scope module standard $end
$upscope $end
$scope module textio $end
$upscope $end
$scope module std_logic_1164 $end
$upscope $end
$scope module numeric_std $end
$upscope $end
$scope module env $end
$upscope $end
$scope module display_tb $end
$var reg 1 ! s_clk $end
$var reg 1 " s_rst $end
$var reg 1 # s_en $end
$var reg 5 $ s_input1[4:0] $end
$var reg 5 % s_input2[4:0] $end
$var reg 5 & s_input3[4:0] $end
$var reg 3 ' s_seg[2:0] $end
$var reg 8 ( s_led[7:0] $end
$scope module dut $end
$var reg 1 ) clk $end
$var reg 1 * rst $end
$var reg 1 + en $end
$var reg 5 , input1[4:0] $end
$var reg 5 - input2[4:0] $end
$var reg 5 . input3[4:0] $end
$var reg 3 / seg[2:0] $end
$var reg 8 0 led[7:0] $end
$var reg 2 1 contador[1:0] $end
$var reg 5 2 s_input[4:0] $end
$upscope $end
$upscope $end
$enddefinitions $end
#0
0!
1"
0#
b00000 $
b00000 %
b00000 &
b000 '
b00000000 (
0)
1*
0+
b00000 ,
b00000 -
b00000 .
b000 /
b11111111 0
b00 1
b00000 2
#5000000
1!
1)
#10000000
0!
0)
#15000000
1!
1)
#20000000
0!
0"
0)
0*
#25000000
1!
1)
#30000000
0!
0)
#35000000
1!
1)
#40000000
0!
1#
0)
1+
#45000000
1!
1)
b00000011 0
b01 1
#50000000
0!
0)
#55000000
1!
1)
b001 /
b10 1
#60000000
0!
0)
#65000000
1!
1)
b010 /
b11 1
#70000000
0!
0)
#75000000
1!
1)
b100 /
b01 1
#80000000
0!
b00001 $
0)
b00001 ,
#85000000
1!
1)
b001 /
b10 1
b00001 2
#90000000
0!
0)
#95000000
1!
1)
b010 /
b10011111 0
b11 1
b00000 2
#100000000
0!
b00010 $
0)
b00010 ,
#105000000
1!
1)
b100 /
b00000011 0
b01 1
#110000000
0!
0)
#115000000
1!
1)
b001 /
b10 1
b00010 2
#120000000
0!
b00011 $
0)
b00011 ,
#125000000
1!
1)
b010 /
b00100101 0
b11 1
b00000 2
#130000000
0!
0)
#135000000
1!
1)
b100 /
b00000011 0
b01 1
#140000000
0!
b00100 $
0)
b00100 ,
#145000000
1!
1)
b001 /
b10 1
b00100 2
#150000000
0!
0)
#155000000
1!
1)
b010 /
b10011001 0
b11 1
b00000 2
#160000000
0!
b00101 $
0)
b00101 ,
#165000000
1!
1)
b100 /
b00000011 0
b01 1
#170000000
0!
0)
#175000000
1!
1)
b001 /
b10 1
b00101 2
#180000000
0!
b00110 $
0)
b00110 ,
#185000000
1!
1)
b010 /
b01001001 0
b11 1
b00000 2
#190000000
0!
0)
#195000000
1!
1)
b100 /
b00000011 0
b01 1
#200000000
0!
b00111 $
0)
b00111 ,
#205000000
1!
1)
b001 /
b10 1
b00111 2
#210000000
0!
0)
#215000000
1!
1)
b010 /
b00011111 0
b11 1
b00000 2
#220000000
0!
b01000 $
0)
b01000 ,
#225000000
1!
1)
b100 /
b00000011 0
b01 1
#230000000
0!
0)
#235000000
1!
1)
b001 /
b10 1
b01000 2
#240000000
0!
b01001 $
0)
b01001 ,
#245000000
1!
1)
b010 /
b00000001 0
b11 1
b00000 2
#250000000
0!
0)
#255000000
1!
1)
b100 /
b00000011 0
b01 1
#260000000
0!
b01010 $
0)
b01010 ,
#265000000
1!
1)
b001 /
b10 1
b01010 2
#270000000
0!
0)
#275000000
1!
1)
b010 /
b00010001 0
b11 1
b00000 2
#280000000
0!
b01011 $
0)
b01011 ,
#285000000
1!
1)
b100 /
b00000011 0
b01 1
#290000000
0!
0)
#295000000
1!
1)
b001 /
b10 1
b01011 2
#300000000
0!
b01100 $
0)
b01100 ,
#305000000
1!
1)
b010 /
b11000001 0
b11 1
b00000 2
#310000000
0!
0)
#315000000
1!
1)
b100 /
b00000011 0
b01 1
#320000000
0!
b01101 $
0)
b01101 ,
#325000000
1!
1)
b001 /
b10 1
b01101 2
#330000000
0!
0)
#335000000
1!
1)
b010 /
b10000101 0
b11 1
b00000 2
#340000000
0!
b01110 $
0)
b01110 ,
#345000000
1!
1)
b100 /
b00000011 0
b01 1
#350000000
0!
0)
#355000000
1!
1)
b001 /
b10 1
b01110 2
#360000000
0!
b01111 $
0)
b01111 ,
#365000000
1!
1)
b010 /
b01100001 0
b11 1
b00000 2
#370000000
0!
0)
#375000000
1!
1)
b100 /
b00000011 0
b01 1
#380000000
0!
0)
#385000000
1!
1)
b001 /
b10 1
b01111 2
#390000000
0!
0)
#395000000
1!
1)
b010 /
b01110001 0
b11 1
b00000 2
#400000000
0!
b00001 %
0)
b00001 -
#405000000
1!
1)
b100 /
b00000011 0
b01 1
#410000000
0!
0)
#415000000
1!
1)
b001 /
b10 1
b01111 2
#420000000
0!
b00010 %
0)
b00010 -
#425000000
1!
1)
b010 /
b01110001 0
b11 1
b00010 2
#430000000
0!
0)
#435000000
1!
1)
b100 /
b00100101 0
b01 1
b00000 2
#440000000
0!
b00011 %
0)
b00011 -
#445000000
1!
1)
b001 /
b00000011 0
b10 1
b01111 2
#450000000
0!
0)
#455000000
1!
1)
b010 /
b01110001 0
b11 1
b00011 2
#460000000
0!
b00100 %
0)
b00100 -
#465000000
1!
1)
b100 /
b00001101 0
b01 1
b00000 2
#470000000
0!
0)
#475000000
1!
1)
b001 /
b00000011 0
b10 1
b01111 2
#480000000
0!
b00101 %
0)
b00101 -
#485000000
1!
1)
b010 /
b01110001 0
b11 1
b00101 2
#490000000
0!
0)
#495000000
1!
1)
b100 /
b01001001 0
b01 1
b00000 2
#500000000
0!
b00110 %
0)
b00110 -
#505000000
1!
1)
b001 /
b00000011 0
b10 1
b01111 2
#510000000
0!
0)
#515000000
1!
1)
b010 /
b01110001 0
b11 1
b00110 2
#520000000
0!
b00111 %
0)
b00111 -
#525000000
1!
1)
b100 /
b01000001 0
b01 1
b00000 2
#530000000
0!
0)
#535000000
1!
1)
b001 /
b00000011 0
b10 1
b01111 2
#540000000
0!
b01000 %
0)
b01000 -
#545000000
1!
1)
b010 /
b01110001 0
b11 1
b01000 2
#550000000
0!
0)
#555000000
1!
1)
b100 /
b00000001 0
b01 1
b00000 2
#560000000
0!
b01001 %
0)
b01001 -
#565000000
1!
1)
b001 /
b00000011 0
b10 1
b01111 2
#570000000
0!
0)
#575000000
1!
1)
b010 /
b01110001 0
b11 1
b01001 2
#580000000
0!
b01010 %
0)
b01010 -
#585000000
1!
1)
b100 /
b00001001 0
b01 1
b00000 2
#590000000
0!
0)
#595000000
1!
1)
b001 /
b00000011 0
b10 1
b01111 2
#600000000
0!
b01011 %
0)
b01011 -
#605000000
1!
1)
b010 /
b01110001 0
b11 1
b01011 2
#610000000
0!
0)
#615000000
1!
1)
b100 /
b11000001 0
b01 1
b00000 2
#620000000
0!
b01100 %
0)
b01100 -
#625000000
1!
1)
b001 /
b00000011 0
b10 1
b01111 2
#630000000
0!
0)
#635000000
1!
1)
b010 /
b01110001 0
b11 1
b01100 2
#640000000
0!
b01101 %
0)
b01101 -
#645000000
1!
1)
b100 /
b01100011 0
b01 1
b00000 2
#650000000
0!
0)
#655000000
1!
1)
b001 /
b00000011 0
b10 1
b01111 2
#660000000
0!
b01110 %
0)
b01110 -
#665000000
1!
1)
b010 /
b01110001 0
b11 1
b01110 2
#670000000
0!
0)
#675000000
1!
1)
b100 /
b01100001 0
b01 1
b00000 2
#680000000
0!
b01111 %
0)
b01111 -
#685000000
1!
1)
b001 /
b00000011 0
b10 1
b01111 2
#690000000
0!
0)
#695000000
1!
1)
b010 /
b01110001 0
b11 1
#700000000
0!
0)
#705000000
1!
1)
b100 /
b01 1
b00000 2
#710000000
0!
0)
#715000000
1!
1)
b001 /
b00000011 0
b10 1
b01111 2
#720000000
0!
b00001 &
0)
b00001 .
#725000000
1!
1)
b010 /
b01110001 0
b11 1
#730000000
0!
0)
#735000000
1!
1)
b100 /
b01 1
b00001 2
#740000000
0!
b00010 &
0)
b00010 .
#745000000
1!
1)
b001 /
b10011111 0
b10 1
b01111 2
#750000000
0!
0)
#755000000
1!
1)
b010 /
b01110001 0
b11 1
#760000000
0!
b00011 &
0)
b00011 .
#765000000
1!
1)
b100 /
b01 1
b00011 2
#770000000
0!
0)
#775000000
1!
1)
b001 /
b00001101 0
b10 1
b01111 2
#780000000
0!
b00100 &
0)
b00100 .
#785000000
1!
1)
b010 /
b01110001 0
b11 1
#790000000
0!
0)
#795000000
1!
1)
b100 /
b01 1
b00100 2
#800000000
0!
b00101 &
0)
b00101 .
#805000000
1!
1)
b001 /
b10011001 0
b10 1
b01111 2
#810000000
0!
0)
#815000000
1!
1)
b010 /
b01110001 0
b11 1
#820000000
0!
b00110 &
0)
b00110 .
#825000000
1!
1)
b100 /
b01 1
b00110 2
#830000000
0!
0)
#835000000
1!
1)
b001 /
b01000001 0
b10 1
b01111 2
#840000000
0!
b00111 &
0)
b00111 .
#845000000
1!
1)
b010 /
b01110001 0
b11 1
#850000000
0!
0)
#855000000
1!
1)
b100 /
b01 1
b00111 2
#860000000
0!
b01000 &
0)
b01000 .
#865000000
1!
1)
b001 /
b00011111 0
b10 1
b01111 2
#870000000
0!
0)
#875000000
1!
1)
b010 /
b01110001 0
b11 1
#880000000
0!
b01001 &
0)
b01001 .
#885000000
1!
1)
b100 /
b01 1
b01001 2
#890000000
0!
0)
#895000000
1!
1)
b001 /
b00001001 0
b10 1
b01111 2
#900000000
0!
b01010 &
0)
b01010 .
#905000000
1!
1)
b010 /
b01110001 0
b11 1
#910000000
0!
0)
#915000000
1!
1)
b100 /
b01 1
b01010 2
#920000000
0!
b01011 &
0)
b01011 .
#925000000
1!
1)
b001 /
b00010001 0
b10 1
b01111 2
#930000000
0!
0)
#935000000
1!
1)
b010 /
b01110001 0
b11 1
#940000000
0!
b01100 &
0)
b01100 .
#945000000
1!
1)
b100 /
b01 1
b01100 2
#950000000
0!
0)
#955000000
1!
1)
b001 /
b01100011 0
b10 1
b01111 2
#960000000
0!
b01101 &
0)
b01101 .
#965000000
1!
1)
b010 /
b01110001 0
b11 1
#970000000
0!
0)
#975000000
1!
1)
b100 /
b01 1
b01101 2
#980000000
0!
b01110 &
0)
b01110 .
#985000000
1!
1)
b001 /
b10000101 0
b10 1
b01111 2
#990000000
0!
0)
#995000000
1!
1)
b010 /
b01110001 0
b11 1
#1000000000
0!
b01111 &
0)
b01111 .
#1005000000
1!
1)
b100 /
b01 1
#1010000000
0!
0)
#1015000000
1!
1)
b001 /
b10 1
#1020000000
0!
1"
0#
0)
1*
0+
b000 /
b11111111 0
b00 1
